livros_da_biblia/__init__.py
livros_da_biblia/livros_da_biblia.py
livros_da_biblia-0.1.0.dist-info/WHEEL
livros_da_biblia-0.1.0.dist-info/METADATA
livros_da_biblia-0.1.0.dist-info/RECORD
