Metadata-Version: 2.1
Name: livros_da_biblia
Version: 0.1.0
Summary: "Retorna os livros da bíblia e divisão por categorias"
License: MIT
Author-email: Elizeu Barbosa Abreu <elizeubarbosaabreu@outlook.com>
Requires-Python: >=3.12
Requires-Dist: requests>=2.32.3
